loadbar/ColorBar.py
loadbar/Colors.py
loadbar/LoadBar.py
loadbar/RainbowBar.py
loadbar/__init__.py
load_bar-0.0.7.dist-info/LICENSE
load_bar-0.0.7.dist-info/METADATA
load_bar-0.0.7.dist-info/WHEEL
load_bar-0.0.7.dist-info/top_level.txt
load_bar-0.0.7.dist-info/RECORD
