Metadata-Version: 2.1
Name: load-bar
Version: 0.0.7
Summary: Python Librairy for a loading bar in the console
Home-page: https://github.com/ValentinVignal/LoadBar
Author: Valentin Vignal
Author-email: valentin.vignal.dev@outlook.fr
License: MIT
Platform: UNKNOWN
Classifier: Programming Language :: Python :: 3
Classifier: License :: OSI Approved :: MIT License
Classifier: Operating System :: OS Independent
Requires-Python: >=3.6
Requires-Dist: termcolor
